src/WIKIDpy/__init__.py
src/WIKIDpy/readscan.py
wikidpy-0.0.1.dist-info/METADATA
wikidpy-0.0.1.dist-info/WHEEL
wikidpy-0.0.1.dist-info/entry_points.txt
wikidpy-0.0.1.dist-info/license_files/LICENSE
wikidpy-0.0.1.dist-info/RECORD
