Metadata-Version: 2.1
Name: wikidpy
Version: 0.0.1
Summary: A python version of MIDAS the MUSTANG2 IDL data analysis software intended to be used with the next generation instrument WIKID
Project-URL: Bug Tracker, https://github.com/sdicker/WIKIDpy/issues
Project-URL: Homepage, https://github.com/sdicker/WIKIDpy
Author-email: Simon Dicker <sdicker@hep.upenn.edu>
Classifier: License :: OSI Approved :: GNU General Public License (GPL)
Classifier: Operating System :: OS Independent
Classifier: Programming Language :: Python :: 3
Requires-Python: >=3.7
